jotformextended.py
jotform_extended-0.1.4.dist-info/licenses/LICENSE
jotform_extended-0.1.4.dist-info/METADATA
jotform_extended-0.1.4.dist-info/WHEEL
jotform_extended-0.1.4.dist-info/top_level.txt
jotform_extended-0.1.4.dist-info/RECORD
